MANIFEST.in
README.md
setup.py
bin/sire
sire/__init__.py
sire/sire.py
sire.egg-info/PKG-INFO
sire.egg-info/SOURCES.txt
sire.egg-info/dependency_links.txt
sire.egg-info/not-zip-safe
sire.egg-info/top_level.txt
templates/.bumpversion.cfg
templates/.coveragerc
templates/.flake8
templates/.gitignore
templates/.pre-commit-config.yaml
templates/.readthedocs.yaml
templates/.travis.yml
templates/CHANGELOG.md
templates/LICENSE
templates/README.md
templates/__init__.py
templates/about.md
templates/index.md
templates/mkdocs.yml
templates/mypy.ini
templates/publish.sh
templates/requirements.txt
templates/setup.py
templates/tests.py