Metadata-Version: 2.1
Name: sire
Version: 1.0.4
Summary: Python project generator
Home-page: http://github.com/interrogator/sire
Author: Danny McDonald
Author-email: mcddjx@gmail.com
License: MIT
Platform: UNKNOWN
